qiskit_aer_gpu-0.15.1.dist-info/METADATA
qiskit_aer_gpu-0.15.1.dist-info/top_level.txt
qiskit_aer_gpu-0.15.1.dist-info/RECORD
qiskit_aer_gpu-0.15.1.dist-info/WHEEL
qiskit_aer_gpu-0.15.1.dist-info/LICENSE.txt
qiskit_aer_gpu.libs/libquadmath-96973f99.so.0.0.0
qiskit_aer_gpu.libs/libgfortran-91cc3cb1.so.3.0.0
qiskit_aer_gpu.libs/libgomp-a34b3233.so.1.0.0
qiskit_aer_gpu.libs/libopenblas-r0-f650aae0.3.3.so
qiskit_aer/aererror.py
qiskit_aer/__init__.py
qiskit_aer/VERSION.txt
qiskit_aer/version.py
qiskit_aer/aerprovider.py
qiskit_aer/library/instructions_table.csv
qiskit_aer/library/__init__.py
qiskit_aer/library/default_qubits.py
qiskit_aer/library/set_instructions/set_statevector.py
qiskit_aer/library/set_instructions/set_unitary.py
qiskit_aer/library/set_instructions/set_superop.py
qiskit_aer/library/set_instructions/__init__.py
qiskit_aer/library/set_instructions/set_density_matrix.py
qiskit_aer/library/set_instructions/set_stabilizer.py
qiskit_aer/library/set_instructions/set_matrix_product_state.py
qiskit_aer/library/save_instructions/save_matrix_product_state.py
qiskit_aer/library/save_instructions/save_state.py
qiskit_aer/library/save_instructions/save_stabilizer.py
qiskit_aer/library/save_instructions/save_probabilities.py
qiskit_aer/library/save_instructions/save_superop.py
qiskit_aer/library/save_instructions/save_statevector.py
qiskit_aer/library/save_instructions/save_clifford.py
qiskit_aer/library/save_instructions/save_density_matrix.py
qiskit_aer/library/save_instructions/save_data.py
qiskit_aer/library/save_instructions/save_expectation_value.py
qiskit_aer/library/save_instructions/__init__.py
qiskit_aer/library/save_instructions/save_amplitudes.py
qiskit_aer/library/save_instructions/save_unitary.py
qiskit_aer/library/control_flow_instructions/jump.py
qiskit_aer/library/control_flow_instructions/__init__.py
qiskit_aer/library/control_flow_instructions/mark.py
qiskit_aer/library/control_flow_instructions/store.py
qiskit_aer/utils/noise_model_inserter.py
qiskit_aer/utils/__init__.py
qiskit_aer/utils/noise_transformation.py
qiskit_aer/backends/name_mapping.py
